matpower/AUTHORS
matpower/CHANGES.md
matpower/CITATION
matpower/CONTRIBUTING.md
matpower/LICENSE
matpower/README.md
matpower/__init__.py
matpower/install_matpower.m
matpower/data/case10ba.m
matpower/data/case118.m
matpower/data/case118zh.m
matpower/data/case12da.m
matpower/data/case1354pegase.m
matpower/data/case13659pegase.m
matpower/data/case136ma.m
matpower/data/case14.m
matpower/data/case141.m
matpower/data/case145.m
matpower/data/case15da.m
matpower/data/case15nbr.m
matpower/data/case16am.m
matpower/data/case16ci.m
matpower/data/case17me.m
matpower/data/case18.m
matpower/data/case1888rte.m
matpower/data/case18nbr.m
matpower/data/case1951rte.m
matpower/data/case22.m
matpower/data/case2383wp.m
matpower/data/case24_ieee_rts.m
matpower/data/case2736sp.m
matpower/data/case2737sop.m
matpower/data/case2746wop.m
matpower/data/case2746wp.m
matpower/data/case2848rte.m
matpower/data/case2868rte.m
matpower/data/case2869pegase.m
matpower/data/case28da.m
matpower/data/case30.m
matpower/data/case300.m
matpower/data/case3012wp.m
matpower/data/case30Q.m
matpower/data/case30pwl.m
matpower/data/case3120sp.m
matpower/data/case3375wp.m
matpower/data/case33bw.m
matpower/data/case33mg.m
matpower/data/case34sa.m
matpower/data/case38si.m
matpower/data/case39.m
matpower/data/case4_dist.m
matpower/data/case4gs.m
matpower/data/case5.m
matpower/data/case51ga.m
matpower/data/case51he.m
matpower/data/case57.m
matpower/data/case6468rte.m
matpower/data/case6470rte.m
matpower/data/case6495rte.m
matpower/data/case6515rte.m
matpower/data/case69.m
matpower/data/case6ww.m
matpower/data/case70da.m
matpower/data/case74ds.m
matpower/data/case85.m
matpower/data/case89pegase.m
matpower/data/case9.m
matpower/data/case9241pegase.m
matpower/data/case94pi.m
matpower/data/case9Q.m
matpower/data/case9target.m
matpower/data/case_ACTIVSg10k.m
matpower/data/case_ACTIVSg200.m
matpower/data/case_ACTIVSg2000.m
matpower/data/case_ACTIVSg25k.m
matpower/data/case_ACTIVSg500.m
matpower/data/case_ACTIVSg70k.m
matpower-7.1.0.2.1.8.dist-info/LICENSE
matpower-7.1.0.2.1.8.dist-info/METADATA
matpower-7.1.0.2.1.8.dist-info/WHEEL
matpower-7.1.0.2.1.8.dist-info/top_level.txt
matpower-7.1.0.2.1.8.dist-info/RECORD
