Metadata-Version: 2.1
Name: matpower
Version: 7.1.0.2.1.8
Summary: matpower-pip: A Python Package for Easy Access to MATPOWER Power System Simulation Package
Author-email: Muhammad Yasirroni <muhammadyasirroni@gmail.com>
Maintainer-email: Muhammad Yasirroni <muhammadyasirroni@gmail.com>
Project-URL: Documentation, https://github.com/yasirroni/matpower-pip#readme
Project-URL: Issues, https://github.com/yasirroni/matpower-pip/issues
Project-URL: Source, https://github.com/yasirroni/matpower-pip
Classifier: Programming Language :: Python
Classifier: Programming Language :: Python :: 3.8
Classifier: Programming Language :: Python :: 3.9
Classifier: Programming Language :: Python :: 3.10
Classifier: Programming Language :: Python :: 3.11
Classifier: Programming Language :: Python :: 3.12
Classifier: Topic :: Scientific/Engineering
Classifier: Topic :: Scientific/Engineering :: Mathematics
Requires-Python: >=3.8.1
License-File: LICENSE
Provides-Extra: dev
Requires-Dist: jupyter >=1.0.0 ; extra == 'dev'
Requires-Dist: matplotlib >=3.5.3 ; extra == 'dev'
Requires-Dist: matpowercaseframes >=1.0.7 ; extra == 'dev'
Requires-Dist: nbmake >=1.3.5 ; extra == 'dev'
Requires-Dist: numpy >=1.21.6 ; extra == 'dev'
Requires-Dist: oct2py >=5.7.0 ; extra == 'dev'
Requires-Dist: openpyxl >=3.1.2 ; extra == 'dev'
Requires-Dist: pandas >=1.3.5 ; extra == 'dev'
Requires-Dist: pypglib >=0.0.1 ; extra == 'dev'
Requires-Dist: pytest >=7.2.0 ; extra == 'dev'
Requires-Dist: pytest-cov >=4.1.0 ; extra == 'dev'
Requires-Dist: pytest-xdist >=3.1.0 ; extra == 'dev'
Requires-Dist: pre-commit >=2.21.0 ; extra == 'dev'
Requires-Dist: ruff >=0.0.254 ; extra == 'dev'
Requires-Dist: setuptools >=68.0.0 ; extra == 'dev'
Provides-Extra: octave
Requires-Dist: oct2py >=5.7.0 ; extra == 'octave'
